pyautokit/__init__.py
pyautokit/__main__.py
pyautokit/api_client.py
pyautokit/backup_manager.py
pyautokit/blockchain_monitor.py
pyautokit/config.py
pyautokit/data_processor.py
pyautokit/email_automation.py
pyautokit/file_organizer.py
pyautokit/github_utils.py
pyautokit/log_analyzer.py
pyautokit/logger.py
pyautokit/playwright_utils.py
pyautokit/py.typed
pyautokit/security_utils.py
pyautokit/task_scheduler.py
pyautokit/utils.py
pyautokit/web_scraper.py
pyautokit-1.0.0.dist-info/licenses/LICENSE
pyautokit-1.0.0.dist-info/METADATA
pyautokit-1.0.0.dist-info/WHEEL
pyautokit-1.0.0.dist-info/entry_points.txt
pyautokit-1.0.0.dist-info/top_level.txt
pyautokit-1.0.0.dist-info/RECORD
