Metadata-Version: 2.4
Name: pyautokit
Version: 1.0.0
Summary: Python Automation Toolkit - Complete CLI utilities for everyday tasks
Home-page: https://github.com/Gzeu/pyautokit
Author: George Pricop
Author-email: George Pricop <contact@georgepricop.com>
Project-URL: Homepage, https://github.com/Gzeu/pyautokit
Project-URL: Bug Tracker, https://github.com/Gzeu/pyautokit/issues
Project-URL: Documentation, https://github.com/Gzeu/pyautokit/blob/main/README.md
Project-URL: Source Code, https://github.com/Gzeu/pyautokit
Project-URL: Examples, https://github.com/Gzeu/pyautokit/tree/main/examples
Keywords: automation,cli,utilities,file-organizer,web-scraper,email-automation,backup,blockchain,crypto,security,data-processing,productivity,playwright,browser-automation,testing,github
Classifier: Development Status :: 4 - Beta
Classifier: Intended Audience :: Developers
Classifier: Intended Audience :: System Administrators
Classifier: Topic :: Software Development :: Libraries :: Python Modules
Classifier: Topic :: System :: Systems Administration
Classifier: Topic :: Utilities
Classifier: License :: OSI Approved :: MIT License
Classifier: Programming Language :: Python :: 3
Classifier: Programming Language :: Python :: 3.9
Classifier: Programming Language :: Python :: 3.10
Classifier: Programming Language :: Python :: 3.11
Classifier: Programming Language :: Python :: 3.12
Classifier: Operating System :: OS Independent
Requires-Python: >=3.9
License-File: LICENSE
Requires-Dist: python-dotenv>=1.0.0
Requires-Dist: requests>=2.31.0
Requires-Dist: beautifulsoup4>=4.12.0
Requires-Dist: lxml>=4.9.0
Requires-Dist: schedule>=1.2.0
Requires-Dist: cryptography>=41.0.0
Provides-Extra: dev
Requires-Dist: pytest>=7.4.0; extra == "dev"
Requires-Dist: pytest-cov>=4.1.0; extra == "dev"
Requires-Dist: pytest-asyncio>=0.21.0; extra == "dev"
Requires-Dist: black>=23.0.0; extra == "dev"
Requires-Dist: flake8>=6.0.0; extra == "dev"
Requires-Dist: mypy>=1.5.0; extra == "dev"
Provides-Extra: watch
Requires-Dist: watchdog>=3.0.0; extra == "watch"
Provides-Extra: browser
Requires-Dist: playwright>=1.40.0; extra == "browser"
Requires-Dist: pytest-asyncio>=0.21.0; extra == "browser"
Provides-Extra: all
Requires-Dist: pytest>=7.4.0; extra == "all"
Requires-Dist: pytest-cov>=4.1.0; extra == "all"
Requires-Dist: pytest-asyncio>=0.21.0; extra == "all"
Requires-Dist: black>=23.0.0; extra == "all"
Requires-Dist: flake8>=6.0.0; extra == "all"
Requires-Dist: mypy>=1.5.0; extra == "all"
Requires-Dist: watchdog>=3.0.0; extra == "all"
Requires-Dist: playwright>=1.40.0; extra == "all"
Dynamic: author
Dynamic: home-page
Dynamic: license-file
Dynamic: requires-python
